git_knapsack-2023.7.28.dist-info/METADATA
git_knapsack-2023.7.28.dist-info/WHEEL
git_knapsack-2023.7.28.dist-info/entry_points.txt
git_knapsack-2023.7.28.dist-info/licenses/LICENSE
git_knapsack.py
git_knapsack-2023.7.28.dist-info/RECORD
